litlyx_sender/__init__.py
litlyx_sender/sender.py
litlyx_sender-0.1.0.dist-info/LICENSE
litlyx_sender-0.1.0.dist-info/METADATA
litlyx_sender-0.1.0.dist-info/WHEEL
litlyx_sender-0.1.0.dist-info/top_level.txt
litlyx_sender-0.1.0.dist-info/RECORD
