Metadata-Version: 2.1
Name: litlyx-sender
Version: 0.1.0
Summary: A Python library for sending events to LitLyx
Home-page: https://github.com/vchaindz/litlyx-sender
Author: Dennis Zimmer
Author-email: dennis@dzlabs.ch
Classifier: Development Status :: 3 - Alpha
Classifier: Intended Audience :: Developers
Classifier: License :: OSI Approved :: MIT License
Classifier: Operating System :: OS Independent
Classifier: Programming Language :: Python :: 3
Classifier: Programming Language :: Python :: 3.6
Classifier: Programming Language :: Python :: 3.7
Classifier: Programming Language :: Python :: 3.8
Classifier: Programming Language :: Python :: 3.9
Requires-Python: >=3.6
License-File: LICENSE
Requires-Dist: requests >=2.25.1
